striplines/__init__.py
striplines/cpw.py
striplines/strip.py
striplines-0.0.2.dist-info/METADATA
striplines-0.0.2.dist-info/WHEEL
striplines-0.0.2.dist-info/top_level.txt
striplines-0.0.2.dist-info/RECORD
